solarpy/__init__.py
solarpy/pvpanel.py
solarpy/radiation.py
solarpy/utils.py
solarpy-0.1.3.dist-info/COPYING
solarpy-0.1.3.dist-info/METADATA
solarpy-0.1.3.dist-info/WHEEL
solarpy-0.1.3.dist-info/top_level.txt
solarpy-0.1.3.dist-info/RECORD
