Metadata-Version: 2.1
Name: solarpy
Version: 0.1.3
Summary: Solar radiation model based on Duffie & Beckman                "Solar energy thermal processes" (1974)
Home-page: https://github.com/aqreed/solarpy
Author: aqreed
License: UNKNOWN
Platform: UNKNOWN
Requires-Dist: numpy
Requires-Dist: matplotlib
